tregex/__init__.py
tregex/tregex.py
tregex_tobiasli-1.0.dist-info/LICENSE
tregex_tobiasli-1.0.dist-info/METADATA
tregex_tobiasli-1.0.dist-info/WHEEL
tregex_tobiasli-1.0.dist-info/top_level.txt
tregex_tobiasli-1.0.dist-info/RECORD
