Metadata-Version: 2.1
Name: tregex-tobiasli
Version: 1.0
Summary: Wrapper for more functionality out of regex parse results.
Home-page: https://github.com/tobiasli/tregex
Author: Tobias Litherland
Author-email: tobiaslland@gmail.com
License: UNKNOWN
Platform: UNKNOWN
Classifier: Programming Language :: Python :: 3
Classifier: License :: OSI Approved :: MIT License
Classifier: Operating System :: OS Independent
